bigdatacorp_wrapper/__init__.py
bigdatacorp_wrapper/company.py
bigdatacorp_wrapper/partner.py
bigdatacorp_wrapper-0.1.0.dist-info/WHEEL
bigdatacorp_wrapper-0.1.0.dist-info/METADATA
bigdatacorp_wrapper-0.1.0.dist-info/RECORD
