Metadata-Version: 2.1
Name: bigdatacorp-wrapper
Version: 0.1.0
Summary: 
Author: Ricardo Gaya
Author-email: rrgaya@gmail.com
Requires-Python: >=3.7,<4.0
Classifier: Programming Language :: Python :: 3
Classifier: Programming Language :: Python :: 3.7
Classifier: Programming Language :: Python :: 3.8
Requires-Dist: python-decouple (>=3.3,<4.0)
Requires-Dist: requests (>=2.23.0,<3.0.0)
